mxmul_FL/__init__.py
mxmul_FL/mxmul.py
mxmul_FL-0.1.1.dist-info/METADATA
mxmul_FL-0.1.1.dist-info/WHEEL
mxmul_FL-0.1.1.dist-info/top_level.txt
mxmul_FL-0.1.1.dist-info/RECORD
