Metadata-Version: 2.1
Name: mxmul-FL
Version: 0.1.1
Summary: An example for teaching how to publish a Python package
Home-page: UNKNOWN
Author: Feng Le
Author-email: 201130933@qq.com
License: UNKNOWN
Platform: UNKNOWN
Classifier: Programming Language :: Python :: 3
Classifier: License :: OSI Approved :: MIT License
Classifier: Operating System :: OS Independent
Requires-Python: >=3.6
